[{"id": "Q13110284", "nameEn": "Alakode Grama Panchayat", "nameMl": "\u0d06\u0d32\u0d15\u0d4d\u0d15\u0d4b\u0d1f\u0d4d \u0d17\u0d4d\u0d30\u0d3e\u0d2e \u0d2a\u0d1e\u0d4d\u0d1a\u0d3e\u0d2f\u0d24\u0d4d\u0d24\u0d4d", "link": "alakode-grama-panchayat"}, {"id": "Q13109827", "nameEn": "Anjarakandy Grama Panchayat", "nameMl": "\u0d05\u0d1e\u0d4d\u0d1a\u0d30\u0d15\u0d4d\u0d15\u0d23\u0d4d\u0d1f\u0d3f \u0d17\u0d4d\u0d30\u0d3e\u0d2e \u0d2a\u0d1e\u0d4d\u0d1a\u0d3e\u0d2f\u0d24\u0d4d\u0d24\u0d4d", "link": "anjarakandy-grama-panchayat"}, {"id": "Q25588003", "nameEn": "Anthoor Municipality", "nameMl": "\u0d06\u0d28\u0d4d\u0d24\u0d42\u0d30\u0d4d \u0d28\u0d17\u0d30\u0d38\u0d2d", "link": "anthoor-municipality"}, {"id": "Q87746071", "nameEn": "Aralam Grama Panchayat", "nameMl": "\u0d06\u0d31\u0d33\u0d02 \u0d17\u0d4d\u0d30\u0d3e\u0d2e \u0d2a\u0d1e\u0d4d\u0d1a\u0d3e\u0d2f\u0d24\u0d4d\u0d24\u0d4d", "link": "aralam-grama-panchayat"}, {"id": "Q13110089", "nameEn": "Ayyankunnu Grama Panchayat", "nameMl": "\u0d05\u0d2f\u0d4d\u0d2f\u0d28\u0d4d\u0d15\u0d41\u0d28\u0d4d\u0d28\u0d4d \u0d17\u0d4d\u0d30\u0d3e\u0d2e \u0d2a\u0d1e\u0d4d\u0d1a\u0d3e\u0d2f\u0d24\u0d4d\u0d24\u0d4d", "link": "ayyankunnu-grama-panchayat"}, {"id": "Q13110137", "nameEn": "Azhikode Grama Panchayat", "nameMl": "\u0d05\u0d34\u0d40\u0d15\u0d4d\u0d15\u0d4b\u0d1f\u0d4d \u0d17\u0d4d\u0d30\u0d3e\u0d2e \u0d2a\u0d1e\u0d4d\u0d1a\u0d3e\u0d2f\u0d24\u0d4d\u0d24\u0d4d", "link": "azhikode-grama-panchayat"}, {"id": "Q16137170", "nameEn": "Chapparapadava Grama Panchayat", "nameMl": "\u0d1a\u0d2a\u0d4d\u0d2a\u0d3e\u0d30\u0d2a\u0d4d\u0d2a\u0d1f\u0d35\u0d4d \u0d17\u0d4d\u0d30\u0d3e\u0d2e \u0d2a\u0d1e\u0d4d\u0d1a\u0d3e\u0d2f\u0d24\u0d4d\u0d24\u0d4d", "link": "chapparapadava-grama-panchayat"}, {"id": "Q16133991", "nameEn": "Chembilode Grama Panchayat", "nameMl": "\u0d1a\u0d46\u0d2e\u0d4d\u0d2a\u0d3f\u0d32\u0d4b\u0d1f\u0d4d \u0d17\u0d4d\u0d30\u0d3e\u0d2e \u0d2a\u0d1e\u0d4d\u0d1a\u0d3e\u0d2f\u0d24\u0d4d\u0d24\u0d4d", "link": "chembilode-grama-panchayat"}, {"id": "Q13112011", "nameEn": "Chengalayi Grama Panchayat", "nameMl": "\u0d1a\u0d46\u0d19\u0d4d\u0d19\u0d33\u0d3e\u0d2f\u0d3f \u0d17\u0d4d\u0d30\u0d3e\u0d2e \u0d2a\u0d1e\u0d4d\u0d1a\u0d3e\u0d2f\u0d24\u0d4d\u0d24\u0d4d", "link": "chengalayi-grama-panchayat"}, {"id": "Q13112044", "nameEn": "Cherukunnu Grama Panchayat", "nameMl": "\u0d1a\u0d46\u0d31\u0d41\u0d15\u0d41\u0d28\u0d4d\u0d28\u0d4d \u0d17\u0d4d\u0d30\u0d3e\u0d2e \u0d2a\u0d1e\u0d4d\u0d1a\u0d3e\u0d2f\u0d24\u0d4d\u0d24\u0d4d", "link": "cherukunnu-grama-panchayat"}, {"id": "Q20578729", "nameEn": "Cherupuzha Grama Panchayat", "nameMl": "\u0d1a\u0d46\u0d31\u0d41\u0d2a\u0d41\u0d34 \u0d17\u0d4d\u0d30\u0d3e\u0d2e \u0d2a\u0d1e\u0d4d\u0d1a\u0d3e\u0d2f\u0d24\u0d4d\u0d24\u0d4d", "link": "cherupuzha-grama-panchayat"}, {"id": "Q887360", "nameEn": "Cheruthazham Grama Panchayat", "nameMl": "\u0d1a\u0d46\u0d31\u0d41\u0d24\u0d3e\u0d34\u0d02 \u0d17\u0d4d\u0d30\u0d3e\u0d2e \u0d2a\u0d1e\u0d4d\u0d1a\u0d3e\u0d2f\u0d24\u0d4d\u0d24\u0d4d", "link": "cheruthazham-grama-panchayat"}, {"id": "Q13111956", "nameEn": "Chirakkal Grama Panchayat", "nameMl": "\u0d1a\u0d3f\u0d31\u0d15\u0d4d\u0d15\u0d32\u0d4d \u0d17\u0d4d\u0d30\u0d3e\u0d2e \u0d2a\u0d1e\u0d4d\u0d1a\u0d3e\u0d2f\u0d24\u0d4d\u0d24\u0d4d", "link": "chirakkal-grama-panchayat"}, {"id": "Q13111963", "nameEn": "Chittariparamba Grama Panchayat", "nameMl": "\u0d1a\u0d3f\u0d31\u0d4d\u0d31\u0d3e\u0d30\u0d3f\u0d2a\u0d4d\u0d2a\u0d31\u0d2e\u0d4d\u0d2a\u0d4d \u0d17\u0d4d\u0d30\u0d3e\u0d2e \u0d2a\u0d1e\u0d4d\u0d1a\u0d3e\u0d2f\u0d24\u0d4d\u0d24\u0d4d", "link": "chittariparamba-grama-panchayat"}, {"id": "Q13112092", "nameEn": "Chokli Grama Panchayat", "nameMl": "\u0d1a\u0d4a\u0d15\u0d4d\u0d33\u0d3f \u0d17\u0d4d\u0d30\u0d3e\u0d2e \u0d2a\u0d1e\u0d4d\u0d1a\u0d3e\u0d2f\u0d24\u0d4d\u0d24\u0d4d", "link": "chokli-grama-panchayat"}, {"id": "Q20580197", "nameEn": "Dharmadam Grama Panchayat", "nameMl": "\u0d27\u0d30\u0d4d\u0d2e\u0d4d\u0d2e\u0d1f\u0d02 \u0d17\u0d4d\u0d30\u0d3e\u0d2e \u0d2a\u0d1e\u0d4d\u0d1a\u0d3e\u0d2f\u0d24\u0d4d\u0d24\u0d4d", "link": "dharmadam-grama-panchayat"}, {"id": "Q16135275", "nameEn": "Eramam Kuttur Grama Panchayat", "nameMl": "\u0d0e\u0d30\u0d2e\u0d02 \u0d15\u0d41\u0d31\u0d4d\u0d31\u0d42\u0d30\u0d4d \u0d17\u0d4d\u0d30\u0d3e\u0d2e \u0d2a\u0d1e\u0d4d\u0d1a\u0d3e\u0d2f\u0d24\u0d4d\u0d24\u0d4d", "link": "eramam-kuttur-grama-panchayat"}, {"id": "Q720219", "nameEn": "Eranholi Grama Panchayat", "nameMl": "\u0d0e\u0d30\u0d1e\u0d4d\u0d1e\u0d4b\u0d33\u0d3f \u0d17\u0d4d\u0d30\u0d3e\u0d2e \u0d2a\u0d1e\u0d4d\u0d1a\u0d3e\u0d2f\u0d24\u0d4d\u0d24\u0d4d", "link": "eranholi-grama-panchayat"}, {"id": "Q13110773", "nameEn": "Eruvessy Grama Panchayat", "nameMl": "\u0d0e\u0d30\u0d41\u0d35\u0d47\u0d36\u0d4d\u0d36\u0d3f \u0d17\u0d4d\u0d30\u0d3e\u0d2e \u0d2a\u0d1e\u0d4d\u0d1a\u0d3e\u0d2f\u0d24\u0d4d\u0d24\u0d4d", "link": "eruvessy-grama-panchayat"}, {"id": "Q5423277", "nameEn": "Ezhome Grama Panchayat", "nameMl": "\u0d0f\u0d34\u0d4b\u0d02 \u0d17\u0d4d\u0d30\u0d3e\u0d2e \u0d2a\u0d1e\u0d4d\u0d1a\u0d3e\u0d2f\u0d24\u0d4d\u0d24\u0d4d", "link": "ezhome-grama-panchayat"}, {"id": "Q16133654", "nameEn": "Irikkur Grama Panchayat", "nameMl": "\u0d07\u0d30\u0d3f\u0d15\u0d4d\u0d15\u0d42\u0d30\u0d4d \u0d17\u0d4d\u0d30\u0d3e\u0d2e \u0d2a\u0d1e\u0d4d\u0d1a\u0d3e\u0d2f\u0d24\u0d4d\u0d24\u0d4d", "link": "irikkur-grama-panchayat"}, {"id": "Q25588302", "nameEn": "Iritty Municipality", "nameMl": "\u0d07\u0d30\u0d3f\u0d1f\u0d4d\u0d1f\u0d3f \u0d28\u0d17\u0d30\u0d38\u0d2d", "link": "iritty-municipality"}, {"id": "Q13110901", "nameEn": "Kadambur Grama Panchayat", "nameMl": "\u0d15\u0d1f\u0d2e\u0d4d\u0d2a\u0d42\u0d30\u0d4d \u0d17\u0d4d\u0d30\u0d3e\u0d2e \u0d2a\u0d1e\u0d4d\u0d1a\u0d3e\u0d2f\u0d24\u0d4d\u0d24\u0d4d", "link": "kadambur-grama-panchayat"}, {"id": "Q20575339", "nameEn": "Kadannappally Panapuzha Grama Panchayat", "nameMl": "\u0d15\u0d1f\u0d28\u0d4d\u0d28\u0d2a\u0d4d\u0d2a\u0d33\u0d4d\u0d33\u0d3f \u0d2a\u0d3e\u0d23\u0d2a\u0d4d\u0d2a\u0d41\u0d34 \u0d17\u0d4d\u0d30\u0d3e\u0d2e \u0d2a\u0d1e\u0d4d\u0d1a\u0d3e\u0d2f\u0d24\u0d4d\u0d24\u0d4d", "link": "kadannappally-panapuzha-grama-panchayat"}, {"id": "Q2456866", "nameEn": "Kadirur Grama Panchayat", "nameMl": "\u0d15\u0d24\u0d3f\u0d30\u0d42\u0d30\u0d4d \u0d17\u0d4d\u0d30\u0d3e\u0d2e \u0d2a\u0d1e\u0d4d\u0d1a\u0d3e\u0d2f\u0d24\u0d4d\u0d24\u0d4d", "link": "kadirur-grama-panchayat"}, {"id": "Q13111076", "nameEn": "Kalliasseri Grama Panchayat", "nameMl": "\u0d15\u0d32\u0d4d\u0d32\u0d4d\u0d2f\u0d3e\u0d36\u0d4d\u0d36\u0d47\u0d30\u0d3f \u0d17\u0d4d\u0d30\u0d3e\u0d2e \u0d2a\u0d1e\u0d4d\u0d1a\u0d3e\u0d2f\u0d24\u0d4d\u0d24\u0d4d", "link": "kalliasseri-grama-panchayat"}, {"id": "Q13110930", "nameEn": "Kanichar Grama Panchayat", "nameMl": "\u0d15\u0d23\u0d3f\u0d1a\u0d4d\u0d1a\u0d3e\u0d30\u0d4d \u0d17\u0d4d\u0d30\u0d3e\u0d2e \u0d2a\u0d1e\u0d4d\u0d1a\u0d3e\u0d2f\u0d24\u0d4d\u0d24\u0d4d", "link": "kanichar-grama-panchayat"}, {"id": "Q13111108", "nameEn": "Kankol - Alappadamba Grama Panchayat", "nameMl": "\u0d15\u0d3e\u0d19\u0d4d\u0d15\u0d4b\u0d32\u0d4d - \u0d06\u0d32\u0d2a\u0d4d\u0d2a\u0d1f\u0d2e\u0d4d\u0d2a \u0d17\u0d4d\u0d30\u0d3e\u0d2e \u0d2a\u0d1e\u0d4d\u0d1a\u0d3e\u0d2f\u0d24\u0d4d\u0d24\u0d4d", "link": "kankol-alappadamba-grama-panchayat"}, {"id": "Q16137200", "nameEn": "Kannapuram Grama Panchayat", "nameMl": "\u0d15\u0d23\u0d4d\u0d23\u0d2a\u0d41\u0d30\u0d02 \u0d17\u0d4d\u0d30\u0d3e\u0d2e \u0d2a\u0d1e\u0d4d\u0d1a\u0d3e\u0d2f\u0d24\u0d4d\u0d24\u0d4d", "link": "kannapuram-grama-panchayat"}, {"id": "Q30645795", "nameEn": "Kannur Municipal Corporation", "nameMl": "\u0d15\u0d23\u0d4d\u0d23\u0d42\u0d7c \u0d2e\u0d41\u0d28\u0d3f\u0d38\u0d3f\u0d2a\u0d4d\u0d2a\u0d7d \u0d15\u0d4b\u0d30\u0d4d\u0d2a\u0d4d\u0d2a\u0d31\u0d47\u0d37\u0d7b", "link": "kannur-municipal-corporation"}, {"id": "Q13111018", "nameEn": "Karivellur Peralam Grama Panchayat", "nameMl": "\u0d15\u0d30\u0d3f\u0d35\u0d46\u0d33\u0d4d\u0d33\u0d42\u0d30\u0d4d \u0d2a\u0d46\u0d30\u0d33\u0d02 \u0d17\u0d4d\u0d30\u0d3e\u0d2e \u0d2a\u0d1e\u0d4d\u0d1a\u0d3e\u0d2f\u0d24\u0d4d\u0d24\u0d4d", "link": "karivellur-peralam-grama-panchayat"}, {"id": "Q16135647", "nameEn": "Keezhallur Grama Panchayat", "nameMl": "\u0d15\u0d40\u0d34\u0d32\u0d4d\u0d32\u0d42\u0d30\u0d4d \u0d17\u0d4d\u0d30\u0d3e\u0d2e \u0d2a\u0d1e\u0d4d\u0d1a\u0d3e\u0d2f\u0d24\u0d4d\u0d24\u0d4d", "link": "keezhallur-grama-panchayat"}, {"id": "Q6385454", "nameEn": "Kelakam Grama Panchayat", "nameMl": "\u0d15\u0d47\u0d33\u0d15\u0d02 \u0d17\u0d4d\u0d30\u0d3e\u0d2e \u0d2a\u0d1e\u0d4d\u0d1a\u0d3e\u0d2f\u0d24\u0d4d\u0d24\u0d4d", "link": "kelakam-grama-panchayat"}, {"id": "Q6426978", "nameEn": "Kolachery Grama Panchayat", "nameMl": "\u0d15\u0d4a\u0d33\u0d1a\u0d4d\u0d1a\u0d47\u0d30\u0d3f \u0d17\u0d4d\u0d30\u0d3e\u0d2e \u0d2a\u0d1e\u0d4d\u0d1a\u0d3e\u0d2f\u0d24\u0d4d\u0d24\u0d4d", "link": "kolachery-grama-panchayat"}, {"id": "Q6427848", "nameEn": "Kolayad Grama Panchayat", "nameMl": "\u0d15\u0d4b\u0d33\u0d2f\u0d3e\u0d1f\u0d4d \u0d17\u0d4d\u0d30\u0d3e\u0d2e \u0d2a\u0d1e\u0d4d\u0d1a\u0d3e\u0d2f\u0d24\u0d4d\u0d24\u0d4d", "link": "kolayad-grama-panchayat"}, {"id": "Q6430512", "nameEn": "Koodali Grama Panchayat", "nameMl": "\u0d15\u0d42\u0d1f\u0d3e\u0d33\u0d3f \u0d17\u0d4d\u0d30\u0d3e\u0d2e \u0d2a\u0d1e\u0d4d\u0d1a\u0d3e\u0d2f\u0d24\u0d4d\u0d24\u0d4d", "link": "koodali-grama-panchayat"}, {"id": "Q16135474", "nameEn": "Kottayam Grama Panchayat", "nameMl": "\u0d15\u0d4b\u0d1f\u0d4d\u0d1f\u0d2f\u0d02 \u0d17\u0d4d\u0d30\u0d3e\u0d2e \u0d2a\u0d1e\u0d4d\u0d1a\u0d3e\u0d2f\u0d24\u0d4d\u0d24\u0d4d", "link": "kottayam-grama-panchayat"}, {"id": "Q13111620", "nameEn": "Kottiyoor Grama Panchayat", "nameMl": "\u0d15\u0d4a\u0d1f\u0d4d\u0d1f\u0d3f\u0d2f\u0d42\u0d30\u0d4d \u0d17\u0d4d\u0d30\u0d3e\u0d2e \u0d2a\u0d1e\u0d4d\u0d1a\u0d3e\u0d2f\u0d24\u0d4d\u0d24\u0d4d", "link": "kottiyoor-grama-panchayat"}, {"id": "Q6444599", "nameEn": "Kunhimangalam Grama Panchayat", "nameMl": "\u0d15\u0d41\u0d1e\u0d4d\u0d1e\u0d3f\u0d2e\u0d02\u0d17\u0d32\u0d02 \u0d17\u0d4d\u0d30\u0d3e\u0d2e \u0d2a\u0d1e\u0d4d\u0d1a\u0d3e\u0d2f\u0d24\u0d4d\u0d24\u0d4d", "link": "kunhimangalam-grama-panchayat"}, {"id": "Q13111322", "nameEn": "Kunnothuparamba Grama Panchayat", "nameMl": "\u0d15\u0d41\u0d28\u0d4d\u0d28\u0d3e\u0d24\u0d4d\u0d24\u0d41\u0d2a\u0d31\u0d2e\u0d4d\u0d2a\u0d4d \u0d17\u0d4d\u0d30\u0d3e\u0d2e \u0d2a\u0d1e\u0d4d\u0d1a\u0d3e\u0d2f\u0d24\u0d4d\u0d24\u0d4d", "link": "kunnothuparamba-grama-panchayat"}, {"id": "Q13111361", "nameEn": "Kurumathur Grama Panchayat", "nameMl": "\u0d15\u0d41\u0d31\u0d41\u0d2e\u0d3e\u0d24\u0d4d\u0d24\u0d42\u0d30\u0d4d \u0d17\u0d4d\u0d30\u0d3e\u0d2e \u0d2a\u0d1e\u0d4d\u0d1a\u0d3e\u0d2f\u0d24\u0d4d\u0d24\u0d4d", "link": "kurumathur-grama-panchayat"}, {"id": "Q16136988", "nameEn": "Kuthuparamba Municipality", "nameMl": "\u0d15\u0d42\u0d24\u0d4d\u0d24\u0d41\u0d2a\u0d31\u0d2e\u0d4d\u0d2a\u0d4d \u0d28\u0d17\u0d30\u0d38\u0d2d", "link": "kuthuparamba-municipality"}, {"id": "Q13111378", "nameEn": "Kuttiattoor Grama Panchayat", "nameMl": "\u0d15\u0d41\u0d31\u0d4d\u0d31\u0d4d\u0d2f\u0d3e\u0d1f\u0d4d\u0d1f\u0d42\u0d30\u0d4d \u0d17\u0d4d\u0d30\u0d3e\u0d2e \u0d2a\u0d1e\u0d4d\u0d1a\u0d3e\u0d2f\u0d24\u0d4d\u0d24\u0d4d", "link": "kuttiattoor-grama-panchayat"}, {"id": "Q6726570", "nameEn": "Madayi Grama Panchayat", "nameMl": "\u0d2e\u0d3e\u0d1f\u0d3e\u0d2f\u0d3f \u0d17\u0d4d\u0d30\u0d3e\u0d2e \u0d2a\u0d1e\u0d4d\u0d1a\u0d3e\u0d2f\u0d24\u0d4d\u0d24\u0d4d", "link": "madayi-grama-panchayat"}, {"id": "Q13564548", "nameEn": "Malappattam Grama Panchayat", "nameMl": "\u0d2e\u0d32\u0d2a\u0d4d\u0d2a\u0d1f\u0d4d\u0d1f\u0d02 \u0d17\u0d4d\u0d30\u0d3e\u0d2e \u0d2a\u0d1e\u0d4d\u0d1a\u0d3e\u0d2f\u0d24\u0d4d\u0d24\u0d4d", "link": "malappattam-grama-panchayat"}, {"id": "Q13114032", "nameEn": "Malur Grama Panchayat", "nameMl": "\u0d2e\u0d3e\u0d32\u0d42\u0d30\u0d4d \u0d17\u0d4d\u0d30\u0d3e\u0d2e \u0d2a\u0d1e\u0d4d\u0d1a\u0d3e\u0d2f\u0d24\u0d4d\u0d24\u0d4d", "link": "malur-grama-panchayat"}, {"id": "Q13113964", "nameEn": "Mangattidam Grama Panchayat", "nameMl": "\u0d2e\u0d3e\u0d19\u0d4d\u0d19\u0d3e\u0d1f\u0d4d\u0d1f\u0d3f\u0d1f\u0d02 \u0d17\u0d4d\u0d30\u0d3e\u0d2e \u0d2a\u0d1e\u0d4d\u0d1a\u0d3e\u0d2f\u0d24\u0d4d\u0d24\u0d4d", "link": "mangattidam-grama-panchayat"}, {"id": "Q13113792", "nameEn": "Mattanur Municipality", "nameMl": "\u0d2e\u0d1f\u0d4d\u0d1f\u0d28\u0d4d\u0d28\u0d42\u0d30\u0d4d \u0d28\u0d17\u0d30\u0d38\u0d2d", "link": "mattanur-municipality"}, {"id": "Q13113985", "nameEn": "Mattool Grama Panchayat", "nameMl": "\u0d2e\u0d3e\u0d1f\u0d4d\u0d1f\u0d42\u0d32\u0d4d \u0d17\u0d4d\u0d30\u0d3e\u0d2e \u0d2a\u0d1e\u0d4d\u0d1a\u0d3e\u0d2f\u0d24\u0d4d\u0d24\u0d4d", "link": "mattool-grama-panchayat"}, {"id": "Q3595935", "nameEn": "Mayyil Grama Panchayat", "nameMl": "\u0d2e\u0d2f\u0d4d\u0d2f\u0d3f\u0d32\u0d4d \u0d17\u0d4d\u0d30\u0d3e\u0d2e \u0d2a\u0d1e\u0d4d\u0d1a\u0d3e\u0d2f\u0d24\u0d4d\u0d24\u0d4d", "link": "mayyil-grama-panchayat"}, {"id": "Q16137878", "nameEn": "Mokeri Grama Panchayat", "nameMl": "\u0d2e\u0d4a\u0d15\u0d47\u0d30\u0d3f \u0d17\u0d4d\u0d30\u0d3e\u0d2e \u0d2a\u0d1e\u0d4d\u0d1a\u0d3e\u0d2f\u0d24\u0d4d\u0d24\u0d4d", "link": "mokeri-grama-panchayat"}, {"id": "Q16137048", "nameEn": "Munderi Grama Panchayat", "nameMl": "\u0d2e\u0d41\u0d23\u0d4d\u0d1f\u0d47\u0d30\u0d3f \u0d17\u0d4d\u0d30\u0d3e\u0d2e \u0d2a\u0d1e\u0d4d\u0d1a\u0d3e\u0d2f\u0d24\u0d4d\u0d24\u0d4d", "link": "munderi-grama-panchayat"}, {"id": "Q16137327", "nameEn": "Muzhakkunnu Grama Panchayat", "nameMl": "\u0d2e\u0d41\u0d34\u0d15\u0d4d\u0d15\u0d41\u0d28\u0d4d\u0d28\u0d4d \u0d17\u0d4d\u0d30\u0d3e\u0d2e \u0d2a\u0d1e\u0d4d\u0d1a\u0d3e\u0d2f\u0d24\u0d4d\u0d24\u0d4d", "link": "muzhakkunnu-grama-panchayat"}, {"id": "Q20582951", "nameEn": "Muzhappilangad Grama Panchayat", "nameMl": "\u0d2e\u0d41\u0d34\u0d2a\u0d4d\u0d2a\u0d3f\u0d32\u0d19\u0d4d\u0d19\u0d3e\u0d1f\u0d4d \u0d17\u0d4d\u0d30\u0d3e\u0d2e \u0d2a\u0d1e\u0d4d\u0d1a\u0d3e\u0d2f\u0d24\u0d4d\u0d24\u0d4d", "link": "muzhappilangad-grama-panchayat"}, {"id": "Q13112791", "nameEn": "Naduvil Grama Panchayat", "nameMl": "\u0d28\u0d1f\u0d41\u0d35\u0d3f\u0d32\u0d4d \u0d17\u0d4d\u0d30\u0d3e\u0d2e \u0d2a\u0d1e\u0d4d\u0d1a\u0d3e\u0d2f\u0d24\u0d4d\u0d24\u0d4d", "link": "naduvil-grama-panchayat"}, {"id": "Q20580392", "nameEn": "Narath Grama Panchayat", "nameMl": "\u0d28\u0d3e\u0d31\u0d3e\u0d24\u0d4d\u0d24\u0d4d \u0d17\u0d4d\u0d30\u0d3e\u0d2e \u0d2a\u0d1e\u0d4d\u0d1a\u0d3e\u0d2f\u0d24\u0d4d\u0d24\u0d4d", "link": "narath-grama-panchayat"}, {"id": "Q2552494", "nameEn": "New Mahe Grama Panchayat", "nameMl": "\u0d28\u0d4d\u0d2f\u0d42 \u0d2e\u0d3e\u0d39\u0d3f \u0d17\u0d4d\u0d30\u0d3e\u0d2e \u0d2a\u0d1e\u0d4d\u0d1a\u0d3e\u0d2f\u0d24\u0d4d\u0d24\u0d4d", "link": "new-mahe-grama-panchayat"}, {"id": "Q13113048", "nameEn": "Padiyoor Grama Panchayat", "nameMl": "\u0d2a\u0d1f\u0d3f\u0d2f\u0d42\u0d30\u0d4d \u0d17\u0d4d\u0d30\u0d3e\u0d2e \u0d2a\u0d1e\u0d4d\u0d1a\u0d3e\u0d2f\u0d24\u0d4d\u0d24\u0d4d", "link": "padiyoor-grama-panchayat"}, {"id": "Q16137365", "nameEn": "Panniyannur Grama Panchayat", "nameMl": "\u0d2a\u0d28\u0d4d\u0d28\u0d4d\u0d2f\u0d28\u0d4d\u0d28\u0d42\u0d30\u0d4d \u0d17\u0d4d\u0d30\u0d3e\u0d2e \u0d2a\u0d1e\u0d4d\u0d1a\u0d3e\u0d2f\u0d24\u0d4d\u0d24\u0d4d", "link": "panniyannur-grama-panchayat"}, {"id": "Q2568336", "nameEn": "Panoor Municipality", "nameMl": "\u0d2a\u0d3e\u0d28\u0d42\u0d7c \u0d28\u0d17\u0d30\u0d38\u0d2d", "link": "panoor-municipality"}, {"id": "Q2475612", "nameEn": "Pappinisseri Grama Panchayat", "nameMl": "\u0d2a\u0d3e\u0d2a\u0d4d\u0d2a\u0d3f\u0d28\u0d3f\u0d36\u0d4d\u0d36\u0d47\u0d30\u0d3f \u0d17\u0d4d\u0d30\u0d3e\u0d2e \u0d2a\u0d1e\u0d4d\u0d1a\u0d3e\u0d2f\u0d24\u0d4d\u0d24\u0d4d", "link": "pappinisseri-grama-panchayat"}, {"id": "Q16137631", "nameEn": "Pariyaram Grama Panchayat", "nameMl": "\u0d2a\u0d30\u0d3f\u0d2f\u0d3e\u0d30\u0d02 \u0d17\u0d4d\u0d30\u0d3e\u0d2e \u0d2a\u0d1e\u0d4d\u0d1a\u0d3e\u0d2f\u0d24\u0d4d\u0d24\u0d4d", "link": "pariyaram-grama-panchayat"}, {"id": "Q2722346", "nameEn": "Pattiam Grama Panchayat", "nameMl": "\u0d2a\u0d3e\u0d1f\u0d4d\u0d2f\u0d02 \u0d17\u0d4d\u0d30\u0d3e\u0d2e \u0d2a\u0d1e\u0d4d\u0d1a\u0d3e\u0d2f\u0d24\u0d4d\u0d24\u0d4d", "link": "pattiam-grama-panchayat"}, {"id": "Q13113058", "nameEn": "Pattuvam Grama Panchayat", "nameMl": "\u0d2a\u0d1f\u0d4d\u0d1f\u0d41\u0d35\u0d02 \u0d17\u0d4d\u0d30\u0d3e\u0d2e \u0d2a\u0d1e\u0d4d\u0d1a\u0d3e\u0d2f\u0d24\u0d4d\u0d24\u0d4d", "link": "pattuvam-grama-panchayat"}, {"id": "Q13113197", "nameEn": "Payam Grama Panchayat", "nameMl": "\u0d2a\u0d3e\u0d2f\u0d02 \u0d17\u0d4d\u0d30\u0d3e\u0d2e \u0d2a\u0d1e\u0d4d\u0d1a\u0d3e\u0d2f\u0d24\u0d4d\u0d24\u0d4d", "link": "payam-grama-panchayat"}, {"id": "Q16137435", "nameEn": "Payyannur Municipality", "nameMl": "\u0d2a\u0d2f\u0d4d\u0d2f\u0d28\u0d4d\u0d28\u0d42\u0d30\u0d4d \u0d28\u0d17\u0d30\u0d38\u0d2d", "link": "payyannur-municipality"}, {"id": "Q3595437", "nameEn": "Payyavoor Grama Panchayat", "nameMl": "\u0d2a\u0d2f\u0d4d\u0d2f\u0d3e\u0d35\u0d42\u0d30\u0d4d \u0d17\u0d4d\u0d30\u0d3e\u0d2e \u0d2a\u0d1e\u0d4d\u0d1a\u0d3e\u0d2f\u0d24\u0d4d\u0d24\u0d4d", "link": "payyavoor-grama-panchayat"}, {"id": "Q2568397", "nameEn": "Peralassery Grama Panchayat", "nameMl": "\u0d2a\u0d46\u0d30\u0d33\u0d36\u0d4d\u0d36\u0d47\u0d30\u0d3f \u0d17\u0d4d\u0d30\u0d3e\u0d2e \u0d2a\u0d1e\u0d4d\u0d1a\u0d3e\u0d2f\u0d24\u0d4d\u0d24\u0d4d", "link": "peralassery-grama-panchayat"}, {"id": "Q13113471", "nameEn": "Peravoor Grama Panchayat", "nameMl": "\u0d2a\u0d47\u0d30\u0d3e\u0d35\u0d42\u0d30\u0d4d \u0d17\u0d4d\u0d30\u0d3e\u0d2e \u0d2a\u0d1e\u0d4d\u0d1a\u0d3e\u0d2f\u0d24\u0d4d\u0d24\u0d4d", "link": "peravoor-grama-panchayat"}, {"id": "Q16136012", "nameEn": "Peringome Vayakkara Grama Panchayat", "nameMl": "\u0d2a\u0d46\u0d30\u0d3f\u0d19\u0d4d\u0d19\u0d4b\u0d02 \u0d35\u0d2f\u0d15\u0d4d\u0d15\u0d30 \u0d17\u0d4d\u0d30\u0d3e\u0d2e \u0d2a\u0d1e\u0d4d\u0d1a\u0d3e\u0d2f\u0d24\u0d4d\u0d24\u0d4d", "link": "peringome-vayakkara-grama-panchayat"}, {"id": "Q16134940", "nameEn": "Pinarayi Grama Panchayat", "nameMl": "\u0d2a\u0d3f\u0d23\u0d31\u0d3e\u0d2f\u0d3f \u0d17\u0d4d\u0d30\u0d3e\u0d2e \u0d2a\u0d1e\u0d4d\u0d1a\u0d3e\u0d2f\u0d24\u0d4d\u0d24\u0d4d", "link": "pinarayi-grama-panchayat"}, {"id": "Q13114362", "nameEn": "Ramanthali Grama Panchayat", "nameMl": "\u0d30\u0d3e\u0d2e\u0d28\u0d4d\u0d24\u0d33\u0d3f \u0d17\u0d4d\u0d30\u0d3e\u0d2e \u0d2a\u0d1e\u0d4d\u0d1a\u0d3e\u0d2f\u0d24\u0d4d\u0d24\u0d4d", "link": "ramanthali-grama-panchayat"}, {"id": "Q16134783", "nameEn": "Sreekandapuram Municipality", "nameMl": "\u0d36\u0d4d\u0d30\u0d40\u0d15\u0d23\u0d4d\u0d20\u0d3e\u0d2a\u0d41\u0d30\u0d02 \u0d28\u0d17\u0d30\u0d38\u0d2d", "link": "sreekandapuram-municipality"}, {"id": "Q13112422", "nameEn": "Thalassery Municipality", "nameMl": "\u0d24\u0d32\u0d36\u0d4d\u0d36\u0d47\u0d30\u0d3f \u0d28\u0d17\u0d30\u0d38\u0d2d", "link": "thalassery-municipality"}, {"id": "Q16136859", "nameEn": "Thalipparamba Municipality", "nameMl": "\u0d24\u0d33\u0d3f\u0d2a\u0d4d\u0d2a\u0d31\u0d2e\u0d4d\u0d2a\u0d4d \u0d28\u0d17\u0d30\u0d38\u0d2d", "link": "thalipparamba-municipality"}, {"id": "Q16137456", "nameEn": "Thillankery Grama Panchayat", "nameMl": "\u0d24\u0d3f\u0d32\u0d4d\u0d32\u0d19\u0d4d\u0d15\u0d47\u0d30\u0d3f \u0d17\u0d4d\u0d30\u0d3e\u0d2e \u0d2a\u0d1e\u0d4d\u0d1a\u0d3e\u0d2f\u0d24\u0d4d\u0d24\u0d4d", "link": "thillankery-grama-panchayat"}, {"id": "Q7798261", "nameEn": "Triprangottoor Grama Panchayat", "nameMl": "\u0d24\u0d43\u0d2a\u0d4d\u0d30\u0d19\u0d4d\u0d19\u0d4b\u0d1f\u0d4d\u0d1f\u0d42\u0d30\u0d4d \u0d17\u0d4d\u0d30\u0d3e\u0d2e \u0d2a\u0d1e\u0d4d\u0d1a\u0d3e\u0d2f\u0d24\u0d4d\u0d24\u0d4d", "link": "triprangottoor-grama-panchayat"}, {"id": "Q16134128", "nameEn": "Udayagiri Grama Panchayat", "nameMl": "\u0d09\u0d26\u0d2f\u0d17\u0d3f\u0d30\u0d3f \u0d17\u0d4d\u0d30\u0d3e\u0d2e \u0d2a\u0d1e\u0d4d\u0d1a\u0d3e\u0d2f\u0d24\u0d4d\u0d24\u0d4d", "link": "udayagiri-grama-panchayat"}, {"id": "Q16134344", "nameEn": "Ulikkal Grama Panchayat", "nameMl": "\u0d09\u0d33\u0d3f\u0d15\u0d4d\u0d15\u0d32\u0d4d \u0d17\u0d4d\u0d30\u0d3e\u0d2e \u0d2a\u0d1e\u0d4d\u0d1a\u0d3e\u0d2f\u0d24\u0d4d\u0d24\u0d4d", "link": "ulikkal-grama-panchayat"}, {"id": "Q13114604", "nameEn": "Valapattanam Grama Panchayat", "nameMl": "\u0d35\u0d33\u0d2a\u0d1f\u0d4d\u0d1f\u0d23\u0d02 \u0d17\u0d4d\u0d30\u0d3e\u0d2e \u0d2a\u0d1e\u0d4d\u0d1a\u0d3e\u0d2f\u0d24\u0d4d\u0d24\u0d4d", "link": "valapattanam-grama-panchayat"}, {"id": "Q16138033", "nameEn": "Vengad Grama Panchayat", "nameMl": "\u0d35\u0d47\u0d19\u0d4d\u0d19\u0d3e\u0d1f\u0d4d \u0d17\u0d4d\u0d30\u0d3e\u0d2e \u0d2a\u0d1e\u0d4d\u0d1a\u0d3e\u0d2f\u0d24\u0d4d\u0d24\u0d4d", "link": "vengad-grama-panchayat"}]